README.txt
setup.py
zopeskel.txt
collective/__init__.py
collective.viewlet.navbar.egg-info/PKG-INFO
collective.viewlet.navbar.egg-info/SOURCES.txt
collective.viewlet.navbar.egg-info/dependency_links.txt
collective.viewlet.navbar.egg-info/entry_points.txt
collective.viewlet.navbar.egg-info/namespace_packages.txt
collective.viewlet.navbar.egg-info/not-zip-safe
collective.viewlet.navbar.egg-info/requires.txt
collective.viewlet.navbar.egg-info/top_level.txt
collective/viewlet/__init__.py
collective/viewlet/navbar/__init__.py
collective/viewlet/navbar/browser.txt
collective/viewlet/navbar/configure.zcml
collective/viewlet/navbar/navbar.pt
collective/viewlet/navbar/navbar.py
collective/viewlet/navbar/tests.py
collective/viewlet/navbar/version.txt
collective/viewlet/navbar/profiles/default/metadata.xml
collective/viewlet/navbar/profiles/default/viewlets.xml
docs/HISTORY.txt
docs/INSTALL.txt
docs/LICENSE.GPL
docs/LICENSE.txt