Metadata-Version: 1.0
Name: collective.viewlet.navbar
Version: 0.1
Summary: Horizontal navigation in a viewlet
Home-page: http://plone.org
Author: Robin Harms Oredsson
Author-email: robin@betahaus.net
License: GPL
Platform: UNKNOWN
Classifier: Framework :: Plone
Classifier: Programming Language :: Python
Classifier: Topic :: Software Development :: Libraries :: Python Modules
